edgar_httpx/__init__.py
edgar_httpx/_version.py
edgar_httpx/controller.py
edgar_httpx/httpclient.py
edgar_httpx/key_generator.py
edgar_httpx/ratelimiter.py
edgar_httpx-0.1.3.dist-info/METADATA
edgar_httpx-0.1.3.dist-info/WHEEL
edgar_httpx-0.1.3.dist-info/licenses/LICENSE
edgar_httpx-0.1.3.dist-info/RECORD
