Metadata-Version: 2.4
Name: edgar_httpx
Version: 0.1.3
Summary: Rate Limiting and Caching HTTPX Client for SEC Edgar Requests
Project-URL: Homepage, https://github.com/paultiq/edgar-httpx
Project-URL: Repository, https://github.com/paultiq/edgar-httpx
Project-URL: Issues, https://github.com/paultiq/edgar-httpx/issues
Author-email: Paul T <paul@iqmo.com>
License-File: LICENSE
Keywords: edgar,hishel,httpx,pyrate_limiter,sec
Classifier: Programming Language :: Python :: 3.9
Classifier: Programming Language :: Python :: 3.10
Classifier: Programming Language :: Python :: 3.11
Classifier: Programming Language :: Python :: 3.12
Classifier: Programming Language :: Python :: 3.13
Classifier: Programming Language :: Python :: 3.14
Requires-Python: >=3.09
Requires-Dist: hishel>=0.1.3
Requires-Dist: pyrate-limiter>=3.9.0
